Metadata-Version: 2.4
Name: mac-messages-mcp-fastmcp
Version: 0.7.4
Summary: A bridge for interacting with macOS Messages app through MCP
Author-email: Carter Lasalle <carterlasalle@gmail.com>
Project-URL: Homepage, https://github.com/fastmcp-me/mac_messages_mcp#readme
Project-URL: Repository, https://github.com/fastmcp-me/mac_messages_mcp.git
Project-URL: Issues, https://github.com/fastmcp-me/mac_messages_mcp/issues
Keywords: macos,messages,imessage,mcp
Classifier: Development Status :: 3 - Alpha
Classifier: Intended Audience :: Developers
Classifier: License :: OSI Approved :: MIT License
Classifier: Programming Language :: Python :: 3
Classifier: Programming Language :: Python :: 3.10
Classifier: Programming Language :: Python :: 3.11
Classifier: Operating System :: MacOS :: MacOS X
Classifier: Topic :: Communications :: Chat
Requires-Python: >=3.10
Requires-Dist: mcp[cli]
Requires-Dist: thefuzz>=0.20.0
Requires-Dist: python-Levenshtein>=0.23.0
Provides-Extra: dev
Requires-Dist: pytest>=7.0.0; extra == "dev"
Requires-Dist: black>=23.0.0; extra == "dev"
Requires-Dist: isort>=5.10.0; extra == "dev"
Requires-Dist: mypy>=1.0.0; extra == "dev"
